zpp_menu/__init__.py
zpp_menu/menu.py
zpp_menu-1.3.2.dist-info/licenses/LICENSE
zpp_menu-1.3.2.dist-info/METADATA
zpp_menu-1.3.2.dist-info/WHEEL
zpp_menu-1.3.2.dist-info/top_level.txt
zpp_menu-1.3.2.dist-info/RECORD
