Metadata-Version: 2.4
Name: zpp_menu
Version: 1.3.2
Summary: Générateur d'un menu à touches fléchées
Home-page: https://github.com/ZephyrOff/zpp_menu
Author: 
License: MIT License
Project-URL: Documentation, https://github.com/ZephyrOff/zpp_menu
Keywords: menu terminal zephyroff
Platform: ALL
Classifier: Development Status :: 5 - Production/Stable
Classifier: Environment :: Console
Classifier: License :: OSI Approved :: MIT License
Classifier: Programming Language :: Python :: 3
License-File: LICENSE
Dynamic: classifier
Dynamic: description
Dynamic: description-content-type
Dynamic: home-page
Dynamic: keywords
Dynamic: license
Dynamic: license-file
Dynamic: platform
Dynamic: project-url
Dynamic: summary
